little_helpers/__init__.py
little_helpers/equinox_helpers.py
little_helpers/gym_helpers.py
little_helpers/rl_helpers.py
little_helper_functions-0.1.0.dist-info/METADATA
little_helper_functions-0.1.0.dist-info/WHEEL
little_helper_functions-0.1.0.dist-info/RECORD
